Metadata-Version: 1.2
Name: journalwriter
Version: 0.0.1
Summary: Write a journal in your favourite text editor with files managed according to date created
Home-page: https://github.com/hemish04082005/journalwriter/
Author: Hemish
Author-email: hemish04082005@gmail.com
License: MIT
Download-URL: https://github.com/hemish04082005/journalwriter/archive/0.0.1.tar.gz
Project-URL: Bug Tracker, https://github.com/hemish04082005/journalwriter/issues
Keywords: python,python3,journal,diary,journals
Platform: any
Classifier: Programming Language :: Python :: 3
Classifier: License :: OSI Approved :: MIT License
Classifier: Operating System :: OS Independent
Requires-Python: >=3.4
